{
  "projects": [
    {
      "title": "Append",
      "current": true,
      "date": "June 2020 - Present",
      "description": "The Future of Networking",
      "repo": "https://github.com/AdvaithNair/graphql-api-template",
      "about": "Append is a platform designed to make sharing ALL contact information extremely convenient through link sharing.",
      "tech": {
        "general": ["GraphQL API", "Postman", "Google OAuth", "Facebook OAuth"],
        "frontend": [
          "TypeScript",
          "ReactJS",
          "React Native",
          "React Context API",
          "Material UI",
          "Apollo Client",
          "Axios",
          "JSON Web Tokens"
        ],
        "backend": [
          "TypeScript",
          "NodeJS",
          "ExpressJS",
          "Express Sessions",
          "PostgreSQL Database",
          "Redis In-Memory Cache",
          "Google Cloud Storage (Bucket Storage)",
          "Type GraphQL",
          "TypeORM",
          "PassportJS OAuth Service"
        ]
      }
    },
    {
      "title": "RANT",
      "current": false,
      "date": "April 2020 - June 2020",
      "description": "The Platform to Vent",
      "repo": "https://github.com/AdvaithNair/rant",
      "site": "https://rant-dd853.web.app/",
      "about": "RANT is a Social Media designed for people to RANT away their frustrations, featuring anonymous, private, and public posting.",
      "tech": {
        "general": ["REST API", "Postman"],
        "frontend": [
          "TypeScript",
          "ReactJS",
          "React Context API",
          "Material UI",
          "Axios",
          "DayJS",
          "JSON Web Tokens",
          "Firebase Hosting"
        ],
        "backend": [
          "TypeScript",
          "NodeJS",
          "ExpressJS",
          "Firebase Cloud Functions (Serverless API Deployment)",
          "Firebase Cloud Firestore (NoSQL Database)",
          "Firebase Cloud Storage (Bucket Storage)"
        ]
      }
    },
    {
      "title": "Aglet",
      "current": false,
      "date": "April 2020 - April 2020",
      "description": "Your Sneaker Collection",
      "repo": "https://github.com/AdvaithNair/aglet",
      "about": "Aglet is a sneaker wishlist app, where users can create, update, and delete sneaker listings featuring fast sorting options.",
      "tech": {
        "general": ["GraphQL API"],
        "frontend": [
          "JavaScript",
          "ReactJS",
          "Material UI",
          "Apollo Client"
        ],
        "backend": [
          "JavaScript",
          "NodeJS",
          "Apollo Server",
          "Prisma GraphQL Yoga Server",
          "MongoDB"
        ]
      }
    },
    {
      "title": "Robotics Scouting",
      "current": false,
      "date": "September 2017 - April 2018",
      "description": "FIRST Robotics Data Analytics Platform",
      "site": "https://play.google.com/store/apps/details?id=overcharged.nair.advaith.relicrecoveryscouting&hl=en_US",
      "about": "FTC Relic Recovery Scouting is an application for robotics students to enter robot match data to generate a ranked list of teams to ally with.",
      "tech": {
        "general": ["Social Media Marketing"],
        "frontend": [
          "Java",
          "XML",
          "Android Studio"
        ],
        "backend": [
          "Java",
          "MySQL"
        ]
      }
    }
  ]
}
